controllermixing-0.1.11.dist-info/licenses/LICENSE
controllers/JaxMod.py
controllers/__init__.py
controllers/models.py
controllers/simulator.py
controllers/utils.py
controllers/Notebooks/AnalyzeSims.ipynb
controllers/Notebooks/Example_NoSlack.ipynb
controllers/Scripts/SimulationScript.py
controllers/Scripts/__init__.py
controllers/data/DataHandling.py
controllers/data/DataProcessing.py
controllers/data/__init__.py
controllers/data/scripts.py
controllers/testdata/nhpdata.pkl
controllermixing-0.1.11.dist-info/METADATA
controllermixing-0.1.11.dist-info/WHEEL
controllermixing-0.1.11.dist-info/top_level.txt
controllermixing-0.1.11.dist-info/RECORD
